tmdb_async_movies/__init__.py
tmdb_async_movies/cli.py
tmdb_async_movies/main.py
tmdb_async_movies/py.typed
tmdb_async_movies-0.1.2.dist-info/LICENSE
tmdb_async_movies-0.1.2.dist-info/METADATA
tmdb_async_movies-0.1.2.dist-info/WHEEL
tmdb_async_movies-0.1.2.dist-info/entry_points.txt
tmdb_async_movies-0.1.2.dist-info/RECORD
