Metadata-Version: 2.1
Name: tmdb_async_movies
Version: 0.1.2
Summary: tmdb-async-movies is an asynchronous utility for fetching bulk movie data from TMDB using movie title and optionally release year.
Home-page: https://github.com/tilschuenemann/tmdb-async-movies
License: MIT
Keywords: tmdb,api,movies,bulk,async,tmdb-api,tmdb-movie,movie,aiohttp,tmdb-async-movies
Author: Til Schünemann
Author-email: til.schuenemann@mailbox.org
Requires-Python: >=3.10,<4.0
Classifier: Development Status :: 3 - Alpha
Classifier: License :: OSI Approved :: MIT License
Classifier: Programming Language :: Python :: 3
Classifier: Programming Language :: Python :: 3.10
Classifier: Programming Language :: Python :: 3.11
Requires-Dist: aiohttp (>=3.8.3,<4.0.0)
Requires-Dist: aiohttp-retry (>=2.8.3,<3.0.0)
Requires-Dist: click (>=8.0.1)
Requires-Dist: numpy (>=1.23.5,<2.0.0)
Requires-Dist: pandas (>=1.5.1,<2.0.0)
Requires-Dist: pathlib (>=1.0.1,<2.0.0)
Requires-Dist: tqdm (>=4.64.1,<5.0.0)
Project-URL: Changelog, https://github.com/tilschuenemann/tmdb-async-movies/releases
Project-URL: Documentation, https://tmdb-async-movies.readthedocs.io
Project-URL: Repository, https://github.com/tilschuenemann/tmdb-async-movies
